Metadata-Version: 2.1
Name: itslight
Version: 0.6
Summary: Get light packages in an instant.
Author-email: AWeirdDev <aweirdscratcher@gmail.com>
License: MIT License
Project-URL: Source, https://github.com/AWeirdScratcher/itslight
Project-URL: Bug Tracker, https://github.com/AWeirdScratcher/itslight/issues
Keywords: light,package,install,get,cli,itslight
Classifier: Programming Language :: Python :: 3
Classifier: License :: OSI Approved :: MIT License
Classifier: Operating System :: OS Independent
Requires-Python: >=3.9
License-File: LICENSE
Requires-Dist: httpx
